nsipptparser/__init__.py
nsipptparser/parse.py
nsipptparser-0.1.1.dist-info/LICENSE
nsipptparser-0.1.1.dist-info/METADATA
nsipptparser-0.1.1.dist-info/WHEEL
nsipptparser-0.1.1.dist-info/top_level.txt
nsipptparser-0.1.1.dist-info/RECORD
