Metadata-Version: 2.1
Name: nsipptparser
Version: 0.1.1
Summary: Very simple package for parsing .nsippt files to json
Home-page: https://github.com/Salk-Harnessing-Plants-Initiative/nsipptparser
Author: Russell Tran
Author-email: tranrl@stanford.edu
License: MIT
Platform: UNKNOWN
Classifier: Development Status :: 2 - Pre-Alpha
Classifier: License :: OSI Approved :: MIT License
Classifier: Programming Language :: Python
Classifier: Programming Language :: Python :: 3.4
Classifier: Programming Language :: Python :: 3.5
Classifier: Programming Language :: Python :: 3.6
Classifier: Programming Language :: Python :: 3.7
